lecoresdk/__init__.py
lecoresdk/credential.py
lecoresdk/fc.py
lecoresdk/iot.py
lecoresdk-1.0.dist-info/METADATA
lecoresdk-1.0.dist-info/RECORD
lecoresdk-1.0.dist-info/WHEEL
lecoresdk-1.0.dist-info/entry_points.txt
lecoresdk-1.0.dist-info/top_level.txt
