Metadata-Version: 2.1
Name: lecoresdk
Version: 1.0
Summary: Link IoT Edge Core SDK for Function Compute
Home-page: https://help.aliyun.com/product/69083.html?spm=a2c4g.11186623.6.540.66bd71b80FSb2h
Author: UNKNOWN
Author-email: UNKNOWN
License: Apache 2.0
Platform: any
Requires-Dist: setuptools (>=16.0)
